nuclick/__init__.py
nuclick/_compat.py
nuclick/_termui_impl.py
nuclick/_textwrap.py
nuclick/_winconsole.py
nuclick/core.py
nuclick/decorators.py
nuclick/exceptions.py
nuclick/formatting.py
nuclick/globals.py
nuclick/parser.py
nuclick/shell_completion.py
nuclick/termui.py
nuclick/testing.py
nuclick/types.py
nuclick/utils.py
nulink_click-0.0.3.dist-info/LICENSE.rst
nulink_click-0.0.3.dist-info/METADATA
nulink_click-0.0.3.dist-info/WHEEL
nulink_click-0.0.3.dist-info/top_level.txt
nulink_click-0.0.3.dist-info/RECORD
