Metadata-Version: 2.1
Name: nulink-click
Version: 0.0.3
Summary: Composable command line interface toolkit
Home-page: https://palletsprojects.com/p/click/
Author: Armin Ronacher
Author-email: armin.ronacher@active-4.com
Maintainer: Pallets
Maintainer-email: contact@palletsprojects.com
License: BSD-3-Clause
Project-URL: Donate, https://palletsprojects.com/donate
Project-URL: Documentation, https://click.palletsprojects.com/
Project-URL: Changes, https://click.palletsprojects.com/changes/
Project-URL: Source Code, https://github.com/pallets/click/
Project-URL: Issue Tracker, https://github.com/pallets/click/issues/
Project-URL: Twitter, https://twitter.com/PalletsTeam
Project-URL: Chat, https://discord.gg/pallets
Platform: UNKNOWN
Classifier: Development Status :: 5 - Production/Stable
Classifier: Intended Audience :: Developers
Classifier: License :: OSI Approved :: BSD License
Classifier: Operating System :: OS Independent
Classifier: Programming Language :: Python
Requires-Python: >=3.7
License-File: LICENSE.rst
Requires-Dist: colorama ; platform_system == "Windows"
Requires-Dist: importlib-metadata ; python_version < "3.8"
